ipeadatapy/__init__.py
ipeadatapy/api_call.py
ipeadatapy/countries.py
ipeadatapy/describe.py
ipeadatapy/latest_updates.py
ipeadatapy/list_series.py
ipeadatapy/metadata.py
ipeadatapy/metadata_old.py
ipeadatapy/sources.py
ipeadatapy/territories.py
ipeadatapy/themes.py
ipeadatapy/timeseries.py
ipeadatapy-0.1.9.dist-info/LICENSE
ipeadatapy-0.1.9.dist-info/METADATA
ipeadatapy-0.1.9.dist-info/WHEEL
ipeadatapy-0.1.9.dist-info/top_level.txt
ipeadatapy-0.1.9.dist-info/RECORD
